dagapp/__init__.py
dagapp/base.py
dagapp/page_funcs.py
dagapp/utils.py
dagapp/examples/__init__.py
dagapp/examples/classification_metric_factory.py
dagapp/examples/configs_example.py
dagapp/examples/simple_example.py
dagapp-0.0.3.dist-info/LICENSE
dagapp-0.0.3.dist-info/METADATA
dagapp-0.0.3.dist-info/WHEEL
dagapp-0.0.3.dist-info/top_level.txt
dagapp-0.0.3.dist-info/RECORD
