Metadata-Version: 2.1
Name: dagapp
Version: 0.0.3
Summary: Making apps from DAGs by just snapping your fingers
Home-page: https://github.com/i2mint/dagapp
Author: OtoSense
License: apache-2.0
Platform: any
Requires-Dist: meshed
Requires-Dist: i2
